<?xml version="1.0" encoding="UTF-8"?>
<objects serializationModel="Studio.02.02.00">
	<object class="AudioFile" id="{dec52698-7e9f-438a-a83d-5fe62360f6ca}">
		<property name="assetPath">
			<value>Final/Ducks/Ducks theme.wav</value>
		</property>
		<property name="isStreaming">
			<value>true</value>
		</property>
		<property name="frequencyInKHz">
			<value>44.0999985</value>
		</property>
		<property name="channelCount">
			<value>2</value>
		</property>
		<property name="length">
			<value>71.875011337868486</value>
		</property>
		<relationship name="masterAssetFolder">
			<destination>{ca117902-401d-4215-a1ac-56fa91d3975e}</destination>
		</relationship>
	</object>
</objects>
